[
  {
    "timestamp": 1509744308874,
    "content": "Ship it personas long shadow viral food-truck minimum viable product thought leader waterfall is so 2000",
    "type": "message",
    "sender": {
      "id": "1",
      "nickname": "Taavi Tervo"
    }
  },
  {
    "timestamp": 1509743994942,
    "content": "Sticky note personas integrate iterate grok thought leader Steve Jobs user story thought leader Steve Jobs workflow disrupt pitch deck.",
    "type": "message",
    "sender": {
      "id": "1",
      "nickname": "Taavi Tervo"
    }
  },
  {
    "timestamp": 1509742308874,
    "content": "Awesome!",
    "type": "message",
    "sender": {
      "id": "2",
      "nickname": "Teme"
    }
  },
  {
    "timestamp": 1509741308874,
    "content": "Ideate thought leader human-centered design ",
    "type": "message",
    "sender": {
      "id": "1",
      "nickname": "Taavi Tervo"
    }
  },
  {
    "timestamp": 1509740308874,
    "content": "Co-working pivot responsive disrupt entrepreneur bootstrapping pivot minimum viable product.",
    "type": "message",
    "sender": {
      "id": "2",
      "nickname": "Teme"
    }
  },
  {
    "timestamp": 1509724308874,
    "content": "Pair programming thinker-maker-doer Steve Jobs.",
    "type": "message",
    "sender": {
      "id": "3",
      "nickname": "Tommi"
    }
  },
  {
    "timestamp": 1509714308874,
    "content": " Ideate intuitive big data quantitative vs. qualitative waterfall is so 2000 and late grok affordances intuitive intuitive user centered design driven workflow. Agile grok iterate entrepreneur cortado iterate ideate engaging entrepreneur engaging ship it.",
    "type": "message",
    "sender": {
      "id": "1",
      "nickname": "Taavi Tervo"
    }
  },
  {
    "timestamp": 1509644308874,
    "content": "LOL",
    "type": "message",
    "sender": {
      "id": "2",
      "nickname": "Teme"
    }
  },
  {
    "timestamp": 1509624308874,
    "content": "Steve Jobs thinker-maker-doer venture capital responsive iterate ship it cortado ship it. 360 campaign workflow integrate paradigm unicorn fund fund quantitative vs. qualitative fund. Prototype innovate engaging hacker 360 campaign entrepreneur user story prototype.",
    "type": "message",
    "sender": {
      "id": "2",
      "nickname": "Teme"
    }
  },
  {
    "timestamp": 1509614308874,
    "content": "Driven grok fund pitch deck ship it pivot user story engaging latte quantitative vs. qualitative experiential SpaceTeam.",
    "type": "message",
    "sender": {
      "id": "3",
      "nickname": "Tommi"
    }
  },
  {
    "timestamp": 1509604308874,
    "content": "Very cool!!!",
    "type": "message",
    "sender": {
      "id": "1",
      "nickname": "Taavi Tervo"
    }
  }
]